wittyPy/__init__.py
wittyPy/wittyPy.py
wittyPy-0.1.dist-info/METADATA
wittyPy-0.1.dist-info/RECORD
wittyPy-0.1.dist-info/WHEEL
wittyPy-0.1.dist-info/top_level.txt
