Metadata-Version: 2.1
Name: wittyPy
Version: 0.1
Summary: A Wrapper for the WittyPi2 Realtime Clock for the RaspberryPi
Home-page: https://github.com/elpunkt/wittyPy
Author: Lucas Langholf
Author-email: lucas@elpunkt.eu
License: UNKNOWN
Platform: UNKNOWN
Classifier: Programming Language :: Python :: 3
Classifier: License :: OSI Approved :: MIT License
Classifier: Operating System :: Unix
